dca_sm_sdk/Exceptions.py
dca_sm_sdk/__init__.py
dca_sm_sdk/mts_state.py
dca_sm_sdk/state_machine.py
dca_sm_sdk-0.0.16.dist-info/licenses/LICENSE
dca_sm_sdk-0.0.16.dist-info/METADATA
dca_sm_sdk-0.0.16.dist-info/WHEEL
dca_sm_sdk-0.0.16.dist-info/top_level.txt
dca_sm_sdk-0.0.16.dist-info/RECORD
